liqfit/__init__.py
liqfit/collators/__init__.py
liqfit/collators/base_collator.py
liqfit/collators/nli_collator.py
liqfit/datasets/__init__.py
liqfit/datasets/nli_dataset.py
liqfit/datasets/transform.py
liqfit/losses/__init__.py
liqfit/losses/losses.py
liqfit/modeling/__init__.py
liqfit/modeling/backbone.py
liqfit/modeling/heads.py
liqfit/modeling/model.py
liqfit/modeling/pooling.py
liqfit/models/__init__.py
liqfit/models/deberta.py
liqfit/models/t5.py
liqfit/pipeline/__init__.py
liqfit/pipeline/inference.py
liqfit/utils/__init__.py
liqfit/utils/metrics.py
liqfit/utils/standardization.py
liqfit/utils/transforms.py
liqfit-1.0.0.dist-info/METADATA
liqfit-1.0.0.dist-info/WHEEL
liqfit-1.0.0.dist-info/licenses/LICENSE
liqfit-1.0.0.dist-info/RECORD
