Metadata-Version: 2.1
Name: liqfit
Version: 1.0.0
Summary: Flexible Few-shot learning tool.
License-Expression: MIT
License-File: LICENSE
Classifier: License :: OSI Approved :: MIT License
Classifier: Operating System :: OS Independent
Classifier: Programming Language :: Python :: 3
Requires-Python: >=3.7
Requires-Dist: accelerate
Requires-Dist: kornia
Requires-Dist: transformers
